{"namespace":"PMDataCareDesignSystem_ac2d54","components":[{"name":"Badge","sourcePath":"components/display/Badge.jsx"},{"name":"Tag","sourcePath":"components/display/Badge.jsx"},{"name":"Card","sourcePath":"components/display/Card.jsx"},{"name":"Dialog","sourcePath":"components/feedback/Dialog.jsx"},{"name":"Toast","sourcePath":"components/feedback/Toast.jsx"},{"name":"Tooltip","sourcePath":"components/feedback/Toast.jsx"},{"name":"Button","sourcePath":"components/forms/Button.jsx"},{"name":"Checkbox","sourcePath":"components/forms/Checkbox.jsx"},{"name":"Radio","sourcePath":"components/forms/Checkbox.jsx"},{"name":"Switch","sourcePath":"components/forms/Checkbox.jsx"},{"name":"IconButton","sourcePath":"components/forms/IconButton.jsx"},{"name":"Field","sourcePath":"components/forms/Input.jsx"},{"name":"Input","sourcePath":"components/forms/Input.jsx"},{"name":"Select","sourcePath":"components/forms/Select.jsx"},{"name":"Textarea","sourcePath":"components/forms/Textarea.jsx"},{"name":"AppHeader","sourcePath":"components/navigation/AppHeader.jsx"},{"name":"Tabs","sourcePath":"components/navigation/Tabs.jsx"}],"startingPoints":[{"name":"Button","path":"components/forms/Button.jsx","previewPath":"components/forms/forms.card.html","kind":"component","section":"Forms","subtitle":"Buttons in all variants and sizes","viewport":"700x220"}],"cards":[{"path":"guidelines/brand-logo-variants.html","group":"Brand","viewport":"700x170","subtitle":"Icon-only for favicons/compact nav · header lockup without tagline","name":"Logo variants"},{"path":"guidelines/brand-logo.html","group":"Brand","viewport":"700x180","subtitle":"Horizontal lockup with tagline · keep tagline at ≥500px width","name":"Logo"},{"path":"guidelines/colors-brand.html","group":"Colors","viewport":"700x150","subtitle":"Core palette from the PM DataCare brand guide","name":"Brand palette"},{"path":"guidelines/colors-feedback.html","group":"Colors","viewport":"700x150","subtitle":"Success / info from the palette; warning & danger are intentional additions","name":"Feedback colors"},{"path":"guidelines/colors-status.html","group":"Colors","viewport":"700x130","subtitle":"Request lifecycle states","name":"Workflow status colors"},{"path":"guidelines/colors-surfaces.html","group":"Colors","viewport":"700x140","subtitle":"Page, card, tint surfaces and border weights","name":"Surfaces & borders"},{"path":"components/display/display.card.html","group":"Components","viewport":"700x260","subtitle":"Card, Badge, Tag","name":"Display"},{"path":"components/feedback/feedback.card.html","group":"Components","viewport":"700x300","subtitle":"Dialog, Toast, Tooltip","name":"Feedback"},{"path":"components/forms/forms.card.html","group":"Components","viewport":"700x400","subtitle":"Button, IconButton, Input, Select, Textarea, Checkbox, Radio, Switch","name":"Forms"},{"path":"components/navigation/navigation.card.html","group":"Components","viewport":"700x220","subtitle":"AppHeader, Tabs","name":"Navigation"},{"path":"ui_kits/portal/index.html","group":"Portal","viewport":"1280x800","subtitle":"Interactive: dashboard, requests queue, new request form, request detail","name":"PM DataCare portal"},{"path":"guidelines/effects-shadows.html","group":"Spacing","viewport":"700x170","subtitle":"Navy-tinted elevation, three levels + focus ring","name":"Shadows"},{"path":"guidelines/spacing-radii.html","group":"Spacing","viewport":"700x150","subtitle":"6 / 10 / 14 / pill","name":"Corner radii"},{"path":"guidelines/spacing-scale.html","group":"Spacing","viewport":"700x140","subtitle":"4px base scale","name":"Spacing scale"},{"path":"guidelines/type-body.html","group":"Type","viewport":"700x160","subtitle":"14px body, 13px secondary, uppercase section labels","name":"Body & labels"},{"path":"guidelines/type-headings.html","group":"Type","viewport":"700x170","subtitle":"Open Sans · navy headings, weight-driven hierarchy","name":"Headings"},{"path":"guidelines/type-weights.html","group":"Type","viewport":"700x130","subtitle":"400/600/700/800 · tabular figures for IDs and counts","name":"Weights & data text"}],"templates":[],"hasThumbnailHtml":true,"globalCssPaths":["tokens/typography.css","tokens/colors.css","tokens/spacing.css","tokens/effects.css","styles.css"],"tokens":[{"name":"--font-ui","value":"\"Open Sans\",\"Segoe UI\",system-ui,sans-serif","kind":"font","definedIn":"tokens/typography.css"},{"name":"--font-display","value":"\"Open Sans\",\"Segoe UI\",system-ui,sans-serif","kind":"font","definedIn":"tokens/typography.css"},{"name":"--text-xs","value":"12px","kind":"font","definedIn":"tokens/typography.css"},{"name":"--text-sm","value":"13px","kind":"font","definedIn":"tokens/typography.css"},{"name":"--text-base","value":"14px","kind":"font","definedIn":"tokens/typography.css"},{"name":"--text-md","value":"16px","kind":"font","definedIn":"tokens/typography.css"},{"name":"--text-lg","value":"18px","kind":"font","definedIn":"tokens/typography.css"},{"name":"--text-xl","value":"22px","kind":"font","definedIn":"tokens/typography.css"},{"name":"--text-2xl","value":"28px","kind":"font","definedIn":"tokens/typography.css"},{"name":"--text-3xl","value":"34px","kind":"font","definedIn":"tokens/typography.css"},{"name":"--leading-tight","value":"1.2","kind":"font","definedIn":"tokens/typography.css"},{"name":"--leading-normal","value":"1.5","kind":"font","definedIn":"tokens/typography.css"},{"name":"--leading-relaxed","value":"1.65","kind":"font","definedIn":"tokens/typography.css"},{"name":"--weight-regular","value":"400","kind":"font","definedIn":"tokens/typography.css"},{"name":"--weight-semibold","value":"600","kind":"font","definedIn":"tokens/typography.css"},{"name":"--weight-bold","value":"700","kind":"font","definedIn":"tokens/typography.css"},{"name":"--weight-extrabold","value":"800","kind":"font","definedIn":"tokens/typography.css"},{"name":"--tracking-caps","value":"0.06em","kind":"font","definedIn":"tokens/typography.css"},{"name":"--navy","value":"#0D3B66","kind":"color","definedIn":"tokens/colors.css"},{"name":"--blue","value":"#1E63D6","kind":"color","definedIn":"tokens/colors.css"},{"name":"--sky","value":"#38A9E0","kind":"color","definedIn":"tokens/colors.css"},{"name":"--teal","value":"#00A79D","kind":"color","definedIn":"tokens/colors.css"},{"name":"--light-blue","value":"#E6F2FA","kind":"color","definedIn":"tokens/colors.css"},{"name":"--surface","value":"#F2F6FA","kind":"color","definedIn":"tokens/colors.css"},{"name":"--slate","value":"#607D8B","kind":"color","definedIn":"tokens/colors.css"},{"name":"--blue-hover","value":"#1854B8","kind":"color","definedIn":"tokens/colors.css"},{"name":"--blue-active","value":"#134497","kind":"color","definedIn":"tokens/colors.css"},{"name":"--teal-hover","value":"#00907F","kind":"color","definedIn":"tokens/colors.css"},{"name":"--sky-tint","value":"#EAF6FC","kind":"color","definedIn":"tokens/colors.css"},{"name":"--teal-tint","value":"#E0F5F3","kind":"color","definedIn":"tokens/colors.css"},{"name":"--navy-tint","value":"#E7EDF4","kind":"color","definedIn":"tokens/colors.css"},{"name":"--text-heading","value":"var(--navy)","kind":"font","definedIn":"tokens/colors.css"},{"name":"--text-body","value":"#33475B","kind":"font","definedIn":"tokens/colors.css"},{"name":"--text-muted","value":"var(--slate)","kind":"font","definedIn":"tokens/colors.css"},{"name":"--text-inverse","value":"#FFFFFF","kind":"font","definedIn":"tokens/colors.css"},{"name":"--text-link","value":"var(--blue)","kind":"font","definedIn":"tokens/colors.css"},{"name":"--text-link-hover","value":"var(--navy)","kind":"font","definedIn":"tokens/colors.css"},{"name":"--surface-page","value":"var(--surface)","kind":"color","definedIn":"tokens/colors.css"},{"name":"--surface-card","value":"#FFFFFF","kind":"color","definedIn":"tokens/colors.css"},{"name":"--surface-tint","value":"var(--light-blue)","kind":"color","definedIn":"tokens/colors.css"},{"name":"--surface-header","value":"#FFFFFF","kind":"color","definedIn":"tokens/colors.css"},{"name":"--surface-inverse","value":"var(--navy)","kind":"color","definedIn":"tokens/colors.css"},{"name":"--accent","value":"var(--blue)","kind":"color","definedIn":"tokens/colors.css"},{"name":"--accent-hover","value":"var(--blue-hover)","kind":"color","definedIn":"tokens/colors.css"},{"name":"--accent-active","value":"var(--blue-active)","kind":"color","definedIn":"tokens/colors.css"},{"name":"--focus-ring","value":"var(--sky)","kind":"color","definedIn":"tokens/colors.css"},{"name":"--border","value":"#D6E2ED","kind":"color","definedIn":"tokens/colors.css"},{"name":"--border-strong","value":"#B9CDDD","kind":"color","definedIn":"tokens/colors.css"},{"name":"--border-input","value":"#C3D4E2","kind":"color","definedIn":"tokens/colors.css"},{"name":"--status-new","value":"var(--sky)","kind":"color","definedIn":"tokens/colors.css"},{"name":"--status-in-progress","value":"var(--blue)","kind":"color","definedIn":"tokens/colors.css"},{"name":"--status-completed","value":"var(--teal)","kind":"color","definedIn":"tokens/colors.css"},{"name":"--status-on-hold","value":"var(--slate)","kind":"color","definedIn":"tokens/colors.css"},{"name":"--status-rejected","value":"#D6455A","kind":"color","definedIn":"tokens/colors.css"},{"name":"--success","value":"var(--teal)","kind":"color","definedIn":"tokens/colors.css"},{"name":"--info","value":"var(--sky)","kind":"color","definedIn":"tokens/colors.css"},{"name":"--warning","value":"#E19A2F","kind":"color","definedIn":"tokens/colors.css"},{"name":"--danger","value":"#D6455A","kind":"color","definedIn":"tokens/colors.css"},{"name":"--success-tint","value":"var(--teal-tint)","kind":"color","definedIn":"tokens/colors.css"},{"name":"--info-tint","value":"var(--sky-tint)","kind":"color","definedIn":"tokens/colors.css"},{"name":"--warning-tint","value":"#FBF1DE","kind":"color","definedIn":"tokens/colors.css"},{"name":"--danger-tint","value":"#FBE7EA","kind":"color","definedIn":"tokens/colors.css"},{"name":"--space-1","value":"4px","kind":"spacing","definedIn":"tokens/spacing.css"},{"name":"--space-2","value":"8px","kind":"spacing","definedIn":"tokens/spacing.css"},{"name":"--space-3","value":"12px","kind":"spacing","definedIn":"tokens/spacing.css"},{"name":"--space-4","value":"16px","kind":"spacing","definedIn":"tokens/spacing.css"},{"name":"--space-5","value":"20px","kind":"spacing","definedIn":"tokens/spacing.css"},{"name":"--space-6","value":"24px","kind":"spacing","definedIn":"tokens/spacing.css"},{"name":"--space-8","value":"32px","kind":"spacing","definedIn":"tokens/spacing.css"},{"name":"--space-10","value":"40px","kind":"spacing","definedIn":"tokens/spacing.css"},{"name":"--space-12","value":"48px","kind":"spacing","definedIn":"tokens/spacing.css"},{"name":"--radius-sm","value":"6px","kind":"radius","definedIn":"tokens/spacing.css"},{"name":"--radius-md","value":"10px","kind":"radius","definedIn":"tokens/spacing.css"},{"name":"--radius-lg","value":"14px","kind":"radius","definedIn":"tokens/spacing.css"},{"name":"--radius-pill","value":"999px","kind":"radius","definedIn":"tokens/spacing.css"},{"name":"--control-h-sm","value":"32px","kind":"spacing","definedIn":"tokens/spacing.css"},{"name":"--control-h-md","value":"40px","kind":"spacing","definedIn":"tokens/spacing.css"},{"name":"--control-h-lg","value":"48px","kind":"spacing","definedIn":"tokens/spacing.css"},{"name":"--container-max","value":"1200px","kind":"spacing","definedIn":"tokens/spacing.css"},{"name":"--shadow-card","value":"0 1px 2px rgba(13,59,102,.06),0 3px 10px rgba(13,59,102,.07)","kind":"shadow","definedIn":"tokens/effects.css"},{"name":"--shadow-raised","value":"0 4px 16px rgba(13,59,102,.12),0 1px 3px rgba(13,59,102,.08)","kind":"shadow","definedIn":"tokens/effects.css"},{"name":"--shadow-overlay","value":"0 12px 40px rgba(13,59,102,.22)","kind":"shadow","definedIn":"tokens/effects.css"},{"name":"--shadow-focus","value":"0 0 0 3px rgba(56,169,224,.35)","kind":"shadow","definedIn":"tokens/effects.css"},{"name":"--ease","value":"cubic-bezier(.4,0,.2,1)","kind":"other","definedIn":"tokens/effects.css","annotation":"other"},{"name":"--dur-fast","value":"120ms","kind":"other","definedIn":"tokens/effects.css","annotation":"other"},{"name":"--dur-med","value":"200ms","kind":"other","definedIn":"tokens/effects.css","annotation":"other"}],"themes":[],"fonts":[],"brandFonts":[{"family":"Open Sans","status":"ok","tokens":["--font-ui","--font-display"],"path":"tokens/typography.css"}],"source":"spa"}